aioworkers_kafka/__init__.py
aioworkers_kafka/consumer.py
aioworkers_kafka/producer.py
aioworkers_kafka/py.typed
aioworkers_kafka/utils.py
aioworkers_kafka-0.2.0.dist-info/METADATA
aioworkers_kafka-0.2.0.dist-info/WHEEL
aioworkers_kafka-0.2.0.dist-info/entry_points.txt
aioworkers_kafka-0.2.0.dist-info/licenses/LICENSE
aioworkers_kafka-0.2.0.dist-info/RECORD
