Metadata-Version: 2.4
Name: aioworkers-kafka
Version: 0.2.0
Summary: aioworkers plugin for kafka
Project-URL: Homepage, https://github.com/aioworkers/aioworkers-kafka
Project-URL: Documentation, https://github.com/aioworkers/aioworkers-kafka#readme
Project-URL: Issues, https://github.com/aioworkers/aioworkers-kafka/issues
Project-URL: Source, https://github.com/aioworkers/aioworkers-kafka
Author-email: Alexander Malev <malev@somedev.ru>
License-Expression: Apache-2.0
License-File: LICENSE
Keywords: aioworkers
Classifier: Development Status :: 4 - Beta
Classifier: Framework :: AsyncIO
Classifier: Intended Audience :: Developers
Classifier: License :: OSI Approved :: Apache Software License
Classifier: Programming Language :: Python :: 3
Classifier: Programming Language :: Python :: 3 :: Only
Classifier: Programming Language :: Python :: 3.9
Classifier: Programming Language :: Python :: 3.10
Classifier: Programming Language :: Python :: 3.11
Classifier: Programming Language :: Python :: 3.12
Classifier: Programming Language :: Python :: 3.13
Classifier: Programming Language :: Python :: Implementation :: CPython
Requires-Python: >=3.9
Requires-Dist: aioworkers>=0.27.0
Requires-Dist: confluent-kafka>=2.3.0
Provides-Extra: dev-lint
Requires-Dist: mypy==1.13.0; extra == 'dev-lint'
Requires-Dist: ruff==0.8.4; extra == 'dev-lint'
Provides-Extra: dev-test
Requires-Dist: aioworkers==0.27.0; extra == 'dev-test'
Requires-Dist: coverage[toml]==7.6.9; extra == 'dev-test'
Requires-Dist: pytest-aioworkers[asyncio]==0.4.0; extra == 'dev-test'
Requires-Dist: pytest-mock==3.14.0; extra == 'dev-test'
Requires-Dist: pytest-timeout==2.3.1; extra == 'dev-test'
Requires-Dist: pytest==8.3.4; extra == 'dev-test'
Requires-Dist: pyyaml==6.0.2; extra == 'dev-test'
